xktools/__init__.py
xktools/database.py
xktools/excel.py
xktools-0.0.1.dist-info/METADATA
xktools-0.0.1.dist-info/WHEEL
xktools-0.0.1.dist-info/top_level.txt
xktools-0.0.1.dist-info/RECORD
