Metadata-Version: 2.1
Name: xktools
Version: 0.0.1
Summary: xktools
Home-page: https://github.com/
Author: davidxiaocn
Author-email: davidxiaocn@qq.com
License: UNKNOWN
Platform: UNKNOWN
Classifier: Programming Language :: Python :: 3
Classifier: License :: OSI Approved :: MIT License
Classifier: Operating System :: OS Independent
